safe_open/__init__.py
safe_open/safe_open.py
safe_open/test.py
safe_open-0.2.1.dist-info/LICENSE
safe_open-0.2.1.dist-info/METADATA
safe_open-0.2.1.dist-info/WHEEL
safe_open-0.2.1.dist-info/top_level.txt
safe_open-0.2.1.dist-info/RECORD
