Metadata-Version: 2.1
Name: safe-open
Version: 0.2.1
Summary: Safe open function
Home-page: https://github.com/lzw65/safe_open
Author: lzw65
Author-email: zhuimengboy65@gmail.com
License: UNKNOWN
Platform: UNKNOWN
License-File: LICENSE
